mj_threads/__init__.py
mj_test_threads-0.0.2.dist-info/METADATA
mj_test_threads-0.0.2.dist-info/WHEEL
mj_test_threads-0.0.2.dist-info/top_level.txt
mj_test_threads-0.0.2.dist-info/RECORD
