Metadata-Version: 2.1
Name: mj-test-threads
Version: 0.0.2
Summary: 线程管理器
Author: MJ
